plottyprint/__init__.py
plottyprint/boxplot.py
plottyprint/histogram.py
plottyprint/scatterplot.py
plottyprint/timeseries.py
plottyprint/utils.py
plottyprint-0.1.dist-info/DESCRIPTION.rst
plottyprint-0.1.dist-info/METADATA
plottyprint-0.1.dist-info/RECORD
plottyprint-0.1.dist-info/WHEEL
plottyprint-0.1.dist-info/metadata.json
plottyprint-0.1.dist-info/top_level.txt
