Metadata-Version: 2.0
Name: plottyprint
Version: 0.1
Summary: provide a couple of easy to use, very basic, printable plots on top of matplotlib
Home-page: https://github.com/paultopia/plottyprint
Author: Paul Gowder
Author-email: paul.gowder@gmail.com
License: MIT
Keywords: plotting,datavis
Platform: UNKNOWN
Classifier: Development Status :: 3 - Alpha
Classifier: Intended Audience :: Developers
Classifier: Intended Audience :: Science/Research
Classifier: License :: OSI Approved :: MIT License
Classifier: Programming Language :: Python :: 3 :: Only
Requires-Python: >=3
Requires-Dist: numpy
Requires-Dist: matplotlib (>=2.1.1)
Requires-Dist: statsmodels
Requires-Dist: scipy
